launchd/__init__.py
launchd/cmd.py
launchd/launchctl.py
launchd/plist.py
launchd/util.py
launchd/tests/__init__.py
launchd/tests/cmd.py
launchd/tests/launchctl.py
launchd/tests/plist.py
launchd-0.3.0.dist-info/AUTHORS
launchd-0.3.0.dist-info/COPYING
launchd-0.3.0.dist-info/METADATA
launchd-0.3.0.dist-info/WHEEL
launchd-0.3.0.dist-info/top_level.txt
launchd-0.3.0.dist-info/RECORD
